ma_fi/__init__.py
ma_fi/download.py
ma_fi-1.0.1.dist-info/METADATA
ma_fi-1.0.1.dist-info/WHEEL
ma_fi-1.0.1.dist-info/top_level.txt
ma_fi-1.0.1.dist-info/RECORD
