Metadata-Version: 2.1
Name: ma-fi
Version: 1.0.1
Summary: Library for accessing financial data of Moroccan stock exchange companies
Home-page: https://github.com/alitalbi/mfinance
Author: Ali Talbi
Author-email: alitalbi73@gmail.com
Classifier: Development Status :: 3 - Alpha
Classifier: Intended Audience :: Developers
Classifier: License :: OSI Approved :: MIT License
Classifier: Programming Language :: Python :: 3
Classifier: Programming Language :: Python :: 3.7
Classifier: Programming Language :: Python :: 3.8
Classifier: Programming Language :: Python :: 3.9
Requires-Dist: pandas
Requires-Dist: numpy
Requires-Dist: requests
